[{"id":1,"name":"c6d09c9de1","money":447,"moneyLine":1310,"moneyBet":-863,"bets":[{"game":{"dbId":1,"id":164022,"team1":"Philadelphia Phillies","team2":"Colorado Rockies","sport":"Baseball","gameDate":1747874400000,"dateClean":"5/22/2025 0:40","team1Odd":0.0,"team2Odd":0.0},"betTeam":"Seattle Mariners","betAmt":10,"winAmt":0,"winOdds":0.0,"numHours":10,"fulfillment":false,"currentEpochSeconds":1748026569,"random":{"deprecated":false},"winOddsOvertime":[[0.0,0.0],[0.0,0.0],[0.0,0.0],[0.0,0.0],[0.0,0.0],[0.0,0.0],[0.0,0.0],[0.0,0.0],[0.0,0.0],[0.0,0.0]],"id":1},{"game":{"dbId":2,"id":164018,"team1":"Los Angeles Angels","team2":"Athletics","sport":"Baseball","gameDate":1747879500000,"dateClean":"5/22/2025 2:05","team1Odd":0.0,"team2Odd":0.0},"betTeam":"Pittsburgh Pirates","betAmt":20,"winAmt":0,"winOdds":0.0,"numHours":10,"fulfillment":false,"currentEpochSeconds":1748026569,"random":{"deprecated":false},"winOddsOvertime":[[0.0,0.0],[0.0,0.0],[0.0,0.0],[0.0,0.0],[0.0,0.0],[0.0,0.0],[0.0,0.0],[0.0,0.0],[0.0,0.0],[0.0,0.0]],"id":2},{"game":{"dbId":3,"id":164019,"team1":"Arizona Diamondbacks","team2":"Los Angeles Dodgers","sport":"Baseball","gameDate":1747879800000,"dateClean":"5/22/2025 2:10","team1Odd":0.0,"team2Odd":0.0},"betTeam":"Chicago Cubs","betAmt":90,"winAmt":0,"winOdds":0.0,"numHours":10,"fulfillment":false,"currentEpochSeconds":1748026569,"random":{"deprecated":false},"winOddsOvertime":[[0.0,0.0],[0.0,0.0],[0.0,0.0],[0.0,0.0],[0.0,0.0],[0.0,0.0],[0.0,0.0],[0.0,0.0],[0.0,0.0],[0.0,0.0]],"id":3},{"game":{"dbId":1,"id":164022,"team1":"Philadelphia Phillies","team2":"Colorado Rockies","sport":"Baseball","gameDate":1747874400000,"dateClean":"5/22/2025 0:40","team1Odd":0.0,"team2Odd":0.0},"betTeam":"Seattle Mariners","betAmt":10,"winAmt":0,"winOdds":0.0,"numHours":10,"fulfillment":false,"currentEpochSeconds":1748026935,"random":{"deprecated":false},"winOddsOvertime":[[0.0,0.0],[0.0,0.0],[0.0,0.0],[0.0,0.0],[0.0,0.0],[0.0,0.0],[0.0,0.0],[0.0,0.0],[0.0,0.0],[0.0,0.0]],"id":4},{"game":{"dbId":2,"id":164018,"team1":"Los Angeles Angels","team2":"Athletics","sport":"Baseball","gameDate":1747879500000,"dateClean":"5/22/2025 2:05","team1Odd":0.0,"team2Odd":0.0},"betTeam":"Pittsburgh Pirates","betAmt":20,"winAmt":0,"winOdds":0.0,"numHours":10,"fulfillment":false,"currentEpochSeconds":1748026935,"random":{"deprecated":false},"winOddsOvertime":[[0.0,0.0],[0.0,0.0],[0.0,0.0],[0.0,0.0],[0.0,0.0],[0.0,0.0],[0.0,0.0],[0.0,0.0],[0.0,0.0],[0.0,0.0]],"id":5},{"game":{"dbId":3,"id":164019,"team1":"Arizona Diamondbacks","team2":"Los Angeles Dodgers","sport":"Baseball","gameDate":1747879800000,"dateClean":"5/22/2025 2:10","team1Odd":0.0,"team2Odd":0.0},"betTeam":"Chicago Cubs","betAmt":90,"winAmt":0,"winOdds":0.0,"numHours":10,"fulfillment":false,"currentEpochSeconds":1748026935,"random":{"deprecated":false},"winOddsOvertime":[[0.0,0.0],[0.0,0.0],[0.0,0.0],[0.0,0.0],[0.0,0.0],[0.0,0.0],[0.0,0.0],[0.0,0.0],[0.0,0.0],[0.0,0.0]],"id":6},{"game":{"dbId":1,"id":164022,"team1":"Philadelphia Phillies","team2":"Colorado Rockies","sport":"Baseball","gameDate":1747874400000,"dateClean":"5/22/2025 0:40","team1Odd":0.0,"team2Odd":0.0},"betTeam":"Seattle Mariners","betAmt":10,"winAmt":0,"winOdds":0.0,"numHours":10,"fulfillment":false,"currentEpochSeconds":1748027025,"random":{"deprecated":false},"winOddsOvertime":[[0.0,0.0],[0.0,0.0],[0.0,0.0],[0.0,0.0],[0.0,0.0],[0.0,0.0],[0.0,0.0],[0.0,0.0],[0.0,0.0],[0.0,0.0]],"id":7},{"game":{"dbId":2,"id":164018,"team1":"Los Angeles Angels","team2":"Athletics","sport":"Baseball","gameDate":1747879500000,"dateClean":"5/22/2025 2:05","team1Odd":0.0,"team2Odd":0.0},"betTeam":"Pittsburgh Pirates","betAmt":20,"winAmt":0,"winOdds":0.0,"numHours":10,"fulfillment":false,"currentEpochSeconds":1748027025,"random":{"deprecated":false},"winOddsOvertime":[[0.0,0.0],[0.0,0.0],[0.0,0.0],[0.0,0.0],[0.0,0.0],[0.0,0.0],[0.0,0.0],[0.0,0.0],[0.0,0.0],[0.0,0.0]],"id":8},{"game":{"dbId":3,"id":164019,"team1":"Arizona Diamondbacks","team2":"Los Angeles Dodgers","sport":"Baseball","gameDate":1747879800000,"dateClean":"5/22/2025 2:10","team1Odd":0.0,"team2Odd":0.0},"betTeam":"Chicago Cubs","betAmt":90,"winAmt":0,"winOdds":0.0,"numHours":10,"fulfillment":false,"currentEpochSeconds":1748027025,"random":{"deprecated":false},"winOddsOvertime":[[0.0,0.0],[0.0,0.0],[0.0,0.0],[0.0,0.0],[0.0,0.0],[0.0,0.0],[0.0,0.0],[0.0,0.0],[0.0,0.0],[0.0,0.0]],"id":9},{"game":{"dbId":1,"id":164022,"team1":"Philadelphia Phillies","team2":"Colorado Rockies","sport":"Baseball","gameDate":1747874400000,"dateClean":"5/22/2025 0:40","team1Odd":0.0,"team2Odd":0.0},"betTeam":"Seattle Mariners","betAmt":10,"winAmt":0,"winOdds":0.0,"numHours":10,"fulfillment":false,"currentEpochSeconds":1748131504,"random":{"deprecated":false},"winOddsOvertime":[[0.0,0.0],[0.0,0.0],[0.0,0.0],[0.0,0.0],[0.0,0.0],[0.0,0.0],[0.0,0.0],[0.0,0.0],[0.0,0.0],[0.0,0.0]],"id":10},{"game":{"dbId":2,"id":164018,"team1":"Los Angeles Angels","team2":"Athletics","sport":"Baseball","gameDate":1747879500000,"dateClean":"5/22/2025 2:05","team1Odd":0.0,"team2Odd":0.0},"betTeam":"Pittsburgh Pirates","betAmt":20,"winAmt":0,"winOdds":0.0,"numHours":10,"fulfillment":false,"currentEpochSeconds":1748131504,"random":{"deprecated":false},"winOddsOvertime":[[0.0,0.0],[0.0,0.0],[0.0,0.0],[0.0,0.0],[0.0,0.0],[0.0,0.0],[0.0,0.0],[0.0,0.0],[0.0,0.0],[0.0,0.0]],"id":11},{"game":{"dbId":3,"id":164019,"team1":"Arizona Diamondbacks","team2":"Los Angeles Dodgers","sport":"Baseball","gameDate":1747879800000,"dateClean":"5/22/2025 2:10","team1Odd":0.0,"team2Odd":0.0},"betTeam":"Chicago Cubs","betAmt":90,"winAmt":0,"winOdds":0.0,"numHours":10,"fulfillment":false,"currentEpochSeconds":1748131504,"random":{"deprecated":false},"winOddsOvertime":[[0.0,0.0],[0.0,0.0],[0.0,0.0],[0.0,0.0],[0.0,0.0],[0.0,0.0],[0.0,0.0],[0.0,0.0],[0.0,0.0],[0.0,0.0]],"id":12},{"game":{"dbId":1,"id":164022,"team1":"Philadelphia Phillies","team2":"Colorado Rockies","sport":"Baseball","gameDate":1747874400000,"dateClean":"5/22/2025 0:40","team1Odd":0.0,"team2Odd":0.0},"betTeam":"Seattle Mariners","betAmt":10,"winAmt":0,"winOdds":0.0,"numHours":10,"fulfillment":false,"currentEpochSeconds":1748131846,"random":{"deprecated":false},"winOddsOvertime":[[0.0,0.0],[0.0,0.0],[0.0,0.0],[0.0,0.0],[0.0,0.0],[0.0,0.0],[0.0,0.0],[0.0,0.0],[0.0,0.0],[0.0,0.0]],"id":13},{"game":{"dbId":2,"id":164018,"team1":"Los Angeles Angels","team2":"Athletics","sport":"Baseball","gameDate":1747879500000,"dateClean":"5/22/2025 2:05","team1Odd":0.0,"team2Odd":0.0},"betTeam":"Pittsburgh Pirates","betAmt":20,"winAmt":0,"winOdds":0.0,"numHours":10,"fulfillment":false,"currentEpochSeconds":1748131846,"random":{"deprecated":false},"winOddsOvertime":[[0.0,0.0],[0.0,0.0],[0.0,0.0],[0.0,0.0],[0.0,0.0],[0.0,0.0],[0.0,0.0],[0.0,0.0],[0.0,0.0],[0.0,0.0]],"id":14},{"game":{"dbId":3,"id":164019,"team1":"Arizona Diamondbacks","team2":"Los Angeles Dodgers","sport":"Baseball","gameDate":1747879800000,"dateClean":"5/22/2025 2:10","team1Odd":0.0,"team2Odd":0.0},"betTeam":"Chicago Cubs","betAmt":90,"winAmt":0,"winOdds":0.0,"numHours":10,"fulfillment":false,"currentEpochSeconds":1748131846,"random":{"deprecated":false},"winOddsOvertime":[[0.0,0.0],[0.0,0.0],[0.0,0.0],[0.0,0.0],[0.0,0.0],[0.0,0.0],[0.0,0.0],[0.0,0.0],[0.0,0.0],[0.0,0.0]],"id":15},{"game":{"dbId":1,"id":164022,"team1":"Philadelphia Phillies","team2":"Colorado Rockies","sport":"Baseball","gameDate":1747874400000,"dateClean":"5/22/2025 0:40","team1Odd":0.0,"team2Odd":0.0},"betTeam":"Seattle Mariners","betAmt":10,"winAmt":0,"winOdds":0.0,"numHours":10,"fulfillment":false,"currentEpochSeconds":1748131933,"random":{"deprecated":false},"winOddsOvertime":[[0.0,0.0],[0.0,0.0],[0.0,0.0],[0.0,0.0],[0.0,0.0],[0.0,0.0],[0.0,0.0],[0.0,0.0],[0.0,0.0],[0.0,0.0]],"id":16},{"game":{"dbId":2,"id":164018,"team1":"Los Angeles Angels","team2":"Athletics","sport":"Baseball","gameDate":1747879500000,"dateClean":"5/22/2025 2:05","team1Odd":0.0,"team2Odd":0.0},"betTeam":"Pittsburgh Pirates","betAmt":20,"winAmt":0,"winOdds":0.0,"numHours":10,"fulfillment":false,"currentEpochSeconds":1748131933,"random":{"deprecated":false},"winOddsOvertime":[[0.0,0.0],[0.0,0.0],[0.0,0.0],[0.0,0.0],[0.0,0.0],[0.0,0.0],[0.0,0.0],[0.0,0.0],[0.0,0.0],[0.0,0.0]],"id":17},{"game":{"dbId":3,"id":164019,"team1":"Arizona Diamondbacks","team2":"Los Angeles Dodgers","sport":"Baseball","gameDate":1747879800000,"dateClean":"5/22/2025 2:10","team1Odd":0.0,"team2Odd":0.0},"betTeam":"Chicago Cubs","betAmt":90,"winAmt":0,"winOdds":0.0,"numHours":10,"fulfillment":false,"currentEpochSeconds":1748131933,"random":{"deprecated":false},"winOddsOvertime":[[0.0,0.0],[0.0,0.0],[0.0,0.0],[0.0,0.0],[0.0,0.0],[0.0,0.0],[0.0,0.0],[0.0,0.0],[0.0,0.0],[0.0,0.0]],"id":18},{"game":{"dbId":1,"id":164022,"team1":"Philadelphia Phillies","team2":"Colorado Rockies","sport":"Baseball","gameDate":1747874400000,"dateClean":"5/22/2025 0:40","team1Odd":0.0,"team2Odd":0.0},"betTeam":"Seattle Mariners","betAmt":10,"winAmt":0,"winOdds":0.0,"numHours":10,"fulfillment":false,"currentEpochSeconds":1748131973,"random":{"deprecated":false},"winOddsOvertime":[[0.0,0.0],[0.0,0.0],[0.0,0.0],[0.0,0.0],[0.0,0.0],[0.0,0.0],[0.0,0.0],[0.0,0.0],[0.0,0.0],[0.0,0.0]],"id":19},{"game":{"dbId":2,"id":164018,"team1":"Los Angeles Angels","team2":"Athletics","sport":"Baseball","gameDate":1747879500000,"dateClean":"5/22/2025 2:05","team1Odd":0.0,"team2Odd":0.0},"betTeam":"Pittsburgh Pirates","betAmt":20,"winAmt":0,"winOdds":0.0,"numHours":10,"fulfillment":false,"currentEpochSeconds":1748131973,"random":{"deprecated":false},"winOddsOvertime":[[0.0,0.0],[0.0,0.0],[0.0,0.0],[0.0,0.0],[0.0,0.0],[0.0,0.0],[0.0,0.0],[0.0,0.0],[0.0,0.0],[0.0,0.0]],"id":20},{"game":{"dbId":3,"id":164019,"team1":"Arizona Diamondbacks","team2":"Los Angeles Dodgers","sport":"Baseball","gameDate":1747879800000,"dateClean":"5/22/2025 2:10","team1Odd":0.0,"team2Odd":0.0},"betTeam":"Chicago Cubs","betAmt":90,"winAmt":0,"winOdds":0.0,"numHours":10,"fulfillment":false,"currentEpochSeconds":1748131973,"random":{"deprecated":false},"winOddsOvertime":[[0.0,0.0],[0.0,0.0],[0.0,0.0],[0.0,0.0],[0.0,0.0],[0.0,0.0],[0.0,0.0],[0.0,0.0],[0.0,0.0],[0.0,0.0]],"id":21},{"game":{"dbId":1,"id":164022,"team1":"Philadelphia Phillies","team2":"Colorado Rockies","sport":"Baseball","gameDate":1747874400000,"dateClean":"5/22/2025 0:40","team1Odd":0.0,"team2Odd":0.0},"betTeam":"Seattle Mariners","betAmt":10,"winAmt":0,"winOdds":0.0,"numHours":10,"fulfillment":false,"currentEpochSeconds":1748132023,"random":{"deprecated":false},"winOddsOvertime":[[0.0,0.0],[0.0,0.0],[0.0,0.0],[0.0,0.0],[0.0,0.0],[0.0,0.0],[0.0,0.0],[0.0,0.0],[0.0,0.0],[0.0,0.0]],"id":22},{"game":{"dbId":2,"id":164018,"team1":"Los Angeles Angels","team2":"Athletics","sport":"Baseball","gameDate":1747879500000,"dateClean":"5/22/2025 2:05","team1Odd":0.0,"team2Odd":0.0},"betTeam":"Pittsburgh Pirates","betAmt":20,"winAmt":0,"winOdds":0.0,"numHours":10,"fulfillment":false,"currentEpochSeconds":1748132023,"random":{"deprecated":false},"winOddsOvertime":[[0.0,0.0],[0.0,0.0],[0.0,0.0],[0.0,0.0],[0.0,0.0],[0.0,0.0],[0.0,0.0],[0.0,0.0],[0.0,0.0],[0.0,0.0]],"id":23},{"game":{"dbId":3,"id":164019,"team1":"Arizona Diamondbacks","team2":"Los Angeles Dodgers","sport":"Baseball","gameDate":1747879800000,"dateClean":"5/22/2025 2:10","team1Odd":0.0,"team2Odd":0.0},"betTeam":"Chicago Cubs","betAmt":90,"winAmt":0,"winOdds":0.0,"numHours":10,"fulfillment":false,"currentEpochSeconds":1748132023,"random":{"deprecated":false},"winOddsOvertime":[[0.0,0.0],[0.0,0.0],[0.0,0.0],[0.0,0.0],[0.0,0.0],[0.0,0.0],[0.0,0.0],[0.0,0.0],[0.0,0.0],[0.0,0.0]],"id":24},{"game":{"dbId":1,"id":164022,"team1":"Philadelphia Phillies","team2":"Colorado Rockies","sport":"Baseball","gameDate":1747874400000,"dateClean":"5/22/2025 0:40","team1Odd":0.0,"team2Odd":0.0},"betTeam":"Seattle Mariners","betAmt":10,"winAmt":0,"winOdds":0.0,"numHours":10,"fulfillment":false,"currentEpochSeconds":1748133029,"random":{"deprecated":false},"winOddsOvertime":[[0.0,0.0],[0.0,0.0],[0.0,0.0],[0.0,0.0],[0.0,0.0],[0.0,0.0],[0.0,0.0],[0.0,0.0],[0.0,0.0],[0.0,0.0]],"id":25},{"game":{"dbId":2,"id":164018,"team1":"Los Angeles Angels","team2":"Athletics","sport":"Baseball","gameDate":1747879500000,"dateClean":"5/22/2025 2:05","team1Odd":0.0,"team2Odd":0.0},"betTeam":"Pittsburgh Pirates","betAmt":20,"winAmt":0,"winOdds":0.0,"numHours":10,"fulfillment":false,"currentEpochSeconds":1748133029,"random":{"deprecated":false},"winOddsOvertime":[[0.0,0.0],[0.0,0.0],[0.0,0.0],[0.0,0.0],[0.0,0.0],[0.0,0.0],[0.0,0.0],[0.0,0.0],[0.0,0.0],[0.0,0.0]],"id":26},{"game":{"dbId":3,"id":164019,"team1":"Arizona Diamondbacks","team2":"Los Angeles Dodgers","sport":"Baseball","gameDate":1747879800000,"dateClean":"5/22/2025 2:10","team1Odd":0.0,"team2Odd":0.0},"betTeam":"Chicago Cubs","betAmt":90,"winAmt":0,"winOdds":0.0,"numHours":10,"fulfillment":false,"currentEpochSeconds":1748133029,"random":{"deprecated":false},"winOddsOvertime":[[0.0,0.0],[0.0,0.0],[0.0,0.0],[0.0,0.0],[0.0,0.0],[0.0,0.0],[0.0,0.0],[0.0,0.0],[0.0,0.0],[0.0,0.0]],"id":27},{"game":{"dbId":1,"id":164022,"team1":"Philadelphia Phillies","team2":"Colorado Rockies","sport":"Baseball","gameDate":1747874400000,"dateClean":"5/22/2025 0:40","team1Odd":0.0,"team2Odd":0.0},"betTeam":"Seattle Mariners","betAmt":10,"winAmt":0,"winOdds":0.0,"numHours":10,"fulfillment":false,"currentEpochSeconds":1748133103,"random":{"deprecated":false},"winOddsOvertime":[[0.0,0.0],[0.0,0.0],[0.0,0.0],[0.0,0.0],[0.0,0.0],[0.0,0.0],[0.0,0.0],[0.0,0.0],[0.0,0.0],[0.0,0.0]],"id":28},{"game":{"dbId":2,"id":164018,"team1":"Los Angeles Angels","team2":"Athletics","sport":"Baseball","gameDate":1747879500000,"dateClean":"5/22/2025 2:05","team1Odd":0.0,"team2Odd":0.0},"betTeam":"Pittsburgh Pirates","betAmt":20,"winAmt":0,"winOdds":0.0,"numHours":10,"fulfillment":false,"currentEpochSeconds":1748133103,"random":{"deprecated":false},"winOddsOvertime":[[0.0,0.0],[0.0,0.0],[0.0,0.0],[0.0,0.0],[0.0,0.0],[0.0,0.0],[0.0,0.0],[0.0,0.0],[0.0,0.0],[0.0,0.0]],"id":29},{"game":{"dbId":3,"id":164019,"team1":"Arizona Diamondbacks","team2":"Los Angeles Dodgers","sport":"Baseball","gameDate":1747879800000,"dateClean":"5/22/2025 2:10","team1Odd":0.0,"team2Odd":0.0},"betTeam":"Chicago Cubs","betAmt":90,"winAmt":0,"winOdds":0.0,"numHours":10,"fulfillment":false,"currentEpochSeconds":1748133103,"random":{"deprecated":false},"winOddsOvertime":[[0.0,0.0],[0.0,0.0],[0.0,0.0],[0.0,0.0],[0.0,0.0],[0.0,0.0],[0.0,0.0],[0.0,0.0],[0.0,0.0],[0.0,0.0]],"id":30},{"game":{"dbId":1,"id":164022,"team1":"Philadelphia Phillies","team2":"Colorado Rockies","sport":"Baseball","gameDate":1747874400000,"dateClean":"5/22/2025 0:40","team1Odd":0.0,"team2Odd":0.0},"betTeam":"Philadelphia Phillies","betAmt":30,"winAmt":81,"winOdds":0.0,"numHours":10,"fulfillment":false,"currentEpochSeconds":1748135508,"random":{"deprecated":false},"winOddsOvertime":[[0.0,0.0],[0.0,0.0],[0.0,0.0],[0.0,0.0],[0.0,0.0],[0.0,0.0],[0.0,0.0],[0.0,0.0],[0.0,0.0],[0.0,0.0]],"id":31},{"game":{"dbId":1,"id":164022,"team1":"Philadelphia Phillies","team2":"Colorado Rockies","sport":"Baseball","gameDate":1747874400000,"dateClean":"5/22/2025 0:40","team1Odd":0.0,"team2Odd":0.0},"betTeam":"Philadelphia Phillies","betAmt":40,"winAmt":108,"winOdds":0.0,"numHours":10,"fulfillment":false,"currentEpochSeconds":1748136304,"random":{"deprecated":false},"winOddsOvertime":[[0.0,0.0],[0.0,0.0],[0.0,0.0],[0.0,0.0],[0.0,0.0],[0.0,0.0],[0.0,0.0],[0.0,0.0],[0.0,0.0],[0.0,0.0]],"id":32},{"game":{"dbId":2,"id":164018,"team1":"Los Angeles Angels","team2":"Athletics","sport":"Baseball","gameDate":1747879500000,"dateClean":"5/22/2025 2:05","team1Odd":0.0,"team2Odd":0.0},"betTeam":"Athletics","betAmt":40,"winAmt":92,"winOdds":0.0,"numHours":10,"fulfillment":false,"currentEpochSeconds":1748136324,"random":{"deprecated":false},"winOddsOvertime":[[0.0,0.0],[0.0,0.0],[0.0,0.0],[0.0,0.0],[0.0,0.0],[0.0,0.0],[0.0,0.0],[0.0,0.0],[0.0,0.0],[0.0,0.0]],"id":33}]},{"id":2,"name":"229c3b39bc","money":971,"moneyLine":0,"moneyBet":971,"bets":[]},{"id":3,"name":"9b54418438","money":193,"moneyLine":0,"moneyBet":193,"bets":[]},{"id":4,"name":"804d21af78","money":3,"moneyLine":0,"moneyBet":3,"bets":[]},{"id":5,"name":"9bc8777a5e","money":220,"moneyLine":0,"moneyBet":220,"bets":[]}]